fzutils/__init__.py
fzutils/aio_utils.py
fzutils/algorithm_utils.py
fzutils/auto_ops_utils.py
fzutils/celery_utils.py
fzutils/common_utils.py
fzutils/cp_utils.py
fzutils/curl_utils.py
fzutils/email_utils.py
fzutils/exceptions.py
fzutils/free_api_utils.py
fzutils/gevent_utils.py
fzutils/img_utils.py
fzutils/internet_utils.py
fzutils/ip_pools.py
fzutils/ip_utils.py
fzutils/items.py
fzutils/iter_utils.py
fzutils/js_utils.py
fzutils/linux_utils.py
fzutils/log_utils.py
fzutils/map_utils.py
fzutils/markdown_utils.py
fzutils/memory_utils.py
fzutils/ocr_utils.py
fzutils/path_utils.py
fzutils/qrcode_utils.py
fzutils/register_utils.py
fzutils/retry_utils.py
fzutils/safe_utils.py
fzutils/shell_utils.py
fzutils/sms_utils.py
fzutils/sniff_utils.py
fzutils/sql_utils.py
fzutils/thread_utils.py
fzutils/time_utils.py
fzutils/tmux_utils.py
fzutils/twisted_utils.py
fzutils/url_utils.py
fzutils/data/__init__.py
fzutils/data/binary_utils.py
fzutils/data/dict_utils.py
fzutils/data/excel_utils.py
fzutils/data/json_utils.py
fzutils/data/list_utils.py
fzutils/data/pickle_utils.py
fzutils/data/queue_utils.py
fzutils/data/str_utils.py
fzutils/spider/__init__.py
fzutils/spider/app_utils.py
fzutils/spider/async_always.py
fzutils/spider/auto.py
fzutils/spider/bloom_utils.py
fzutils/spider/chrome_extensions.py
fzutils/spider/chrome_remote_interface.py
fzutils/spider/crawler.py
fzutils/spider/fz_aiohttp.py
fzutils/spider/fz_driver.py
fzutils/spider/fz_phantomjs.py
fzutils/spider/fz_requests.py
fzutils/spider/pyppeteer_always.py
fzutils/spider/selector.py
fzutils/spider/selenium_always.py
fzutils/spider/templates/__init__.py
fzutils/spider/templates/config.py
fzutils-0.4.1.3.dist-info/LICENSE.txt
fzutils-0.4.1.3.dist-info/METADATA
fzutils-0.4.1.3.dist-info/WHEEL
fzutils-0.4.1.3.dist-info/top_level.txt
fzutils-0.4.1.3.dist-info/zip-safe
fzutils-0.4.1.3.dist-info/RECORD
