Metadata-Version: 2.1
Name: fzutils
Version: 0.4.1.3
Summary: A Python utils for spider
Home-page: https://www.github.com/superonesfazai
Author: super_fazai
Author-email: superonesfazai@gmail.com
License: MIT
Platform: linux/Windows/Mac
Classifier: Programming Language :: Python :: 3 :: Only
Classifier: License :: OSI Approved :: MIT License
Classifier: Intended Audience :: Developers
Classifier: Operating System :: OS Independent
Requires-Python: >=3
Requires-Dist: wheel
Requires-Dist: pysocks
Requires-Dist: requests
Requires-Dist: requests-oauthlib
Requires-Dist: selenium (==3.8.0)
Requires-Dist: uvloop
Requires-Dist: asyncio
Requires-Dist: nest-asyncio
Requires-Dist: psutil
Requires-Dist: pyexecjs
Requires-Dist: setuptools
Requires-Dist: numpy
Requires-Dist: pprint
Requires-Dist: chardet
Requires-Dist: scrapy
Requires-Dist: greenlet (==0.4.14)
Requires-Dist: gevent
Requires-Dist: aiohttp
Requires-Dist: celery
Requires-Dist: flower
Requires-Dist: pyexcel
Requires-Dist: pyexcel-xlsx
Requires-Dist: fabric
Requires-Dist: jieba
Requires-Dist: elasticsearch
Requires-Dist: elasticsearch-dsl
Requires-Dist: salt
Requires-Dist: baidu-aip
Requires-Dist: fonttools
Requires-Dist: xmltodict
Requires-Dist: ftfy
Requires-Dist: tenacity
Requires-Dist: pyzbar
Requires-Dist: termcolor
Requires-Dist: pypinyin
Requires-Dist: bitarray
Requires-Dist: click
Requires-Dist: websockets (==7.0)
Requires-Dist: pyppeteer
Requires-Dist: bunch
Requires-Dist: better-exceptions
Requires-Dist: scapy
Requires-Dist: scapy-http
Requires-Dist: demjson
Requires-Dist: jsonpath
Requires-Dist: pytz
Requires-Dist: python-dateutil
Requires-Dist: pymssql
Requires-Dist: sqlalchemy
Requires-Dist: pymongo
Requires-Dist: redis
Requires-Dist: mongoengine
Requires-Dist: prettytable
Requires-Dist: pika
